{
    "xyz":[
        {
            "attendance_id": 1,
            "employee_id": 1,
            "attendance_date": "2024-03-31T18:30:00.000Z",
            "status": "Present"
        },
        {
            "attendance_id": 2,
            "employee_id": 2,
            "attendance_date": "2024-03-31T18:30:00.000Z",
            "status": "Absent"
        },
        {
            "attendance_id": 3,
            "employee_id": 3,
            "attendance_date": "2024-03-31T18:30:00.000Z",
            "status": "Present"
        },
        {
            "attendance_id": 4,
            "employee_id": 4,
            "attendance_date": "2024-03-31T18:30:00.000Z",
            "status": "Absent"
        },
        {
            "attendance_id": 5,
            "employee_id": 5,
            "attendance_date": "2024-03-31T18:30:00.000Z",
            "status": "Present"
        },
        {
            "attendance_id": 6,
            "employee_id": 6,
            "attendance_date": "2024-03-31T18:30:00.000Z",
            "status": "Absent"
        },
        {
            "attendance_id": 7,
            "employee_id": 7,
            "attendance_date": "2024-03-31T18:30:00.000Z",
            "status": "Present"
        },
        {
            "attendance_id": 8,
            "employee_id": 8,
            "attendance_date": "2024-03-31T18:30:00.000Z",
            "status": "Present"
        },
        {
            "attendance_id": 9,
            "employee_id": 9,
            "attendance_date": "2024-03-31T18:30:00.000Z",
            "status": "Absent"
        },
        {
            "attendance_id": 10,
            "employee_id": 10,
            "attendance_date": "2024-03-31T18:30:00.000Z",
            "status": "Present"
        },
        {
            "attendance_id": 11,
            "employee_id": 1,
            "attendance_date": "2024-04-01T18:30:00.000Z",
            "status": "Absent"
        },
        {
            "attendance_id": 12,
            "employee_id": 2,
            "attendance_date": "2024-04-01T18:30:00.000Z",
            "status": "Present"
        },
        {
            "attendance_id": 13,
            "employee_id": 3,
            "attendance_date": "2024-04-01T18:30:00.000Z",
            "status": "Present"
        },
        {
            "attendance_id": 14,
            "employee_id": 4,
            "attendance_date": "2024-04-01T18:30:00.000Z",
            "status": "Late"
        },
        {
            "attendance_id": 15,
            "employee_id": 5,
            "attendance_date": "2024-04-01T18:30:00.000Z",
            "status": "Present"
        },
        {
            "attendance_id": 16,
            "employee_id": 6,
            "attendance_date": "2024-04-01T18:30:00.000Z",
            "status": "Absent"
        },
        {
            "attendance_id": 17,
            "employee_id": 7,
            "attendance_date": "2024-04-01T18:30:00.000Z",
            "status": "Present"
        },
        {
            "attendance_id": 18,
            "employee_id": 8,
            "attendance_date": "2024-04-01T18:30:00.000Z",
            "status": "Present"
        },
        {
            "attendance_id": 19,
            "employee_id": 9,
            "attendance_date": "2024-04-01T18:30:00.000Z",
            "status": "Absent"
        },
        {
            "attendance_id": 20,
            "employee_id": 10,
            "attendance_date": "2024-04-01T18:30:00.000Z",
            "status": "Present"
        },
        {
            "attendance_id": 21,
            "employee_id": 1,
            "attendance_date": "2024-04-02T18:30:00.000Z",
            "status": "Present"
        },
        {
            "attendance_id": 22,
            "employee_id": 2,
            "attendance_date": "2024-04-02T18:30:00.000Z",
            "status": "Present"
        },
        {
            "attendance_id": 23,
            "employee_id": 3,
            "attendance_date": "2024-04-02T18:30:00.000Z",
            "status": "Absent"
        },
        {
            "attendance_id": 24,
            "employee_id": 4,
            "attendance_date": "2024-04-02T18:30:00.000Z",
            "status": "Present"
        },
        {
            "attendance_id": 25,
            "employee_id": 5,
            "attendance_date": "2024-04-02T18:30:00.000Z",
            "status": "Late"
        },
        {
            "attendance_id": 26,
            "employee_id": 6,
            "attendance_date": "2024-04-02T18:30:00.000Z",
            "status": "Absent"
        },
        {
            "attendance_id": 27,
            "employee_id": 7,
            "attendance_date": "2024-04-02T18:30:00.000Z",
            "status": "Present"
        },
        {
            "attendance_id": 28,
            "employee_id": 8,
            "attendance_date": "2024-04-02T18:30:00.000Z",
            "status": "Present"
        },
        {
            "attendance_id": 29,
            "employee_id": 9,
            "attendance_date": "2024-04-02T18:30:00.000Z",
            "status": "Present"
        },
        {
            "attendance_id": 30,
            "employee_id": 10,
            "attendance_date": "2024-04-02T18:30:00.000Z",
            "status": "Absent"
        },
        {
            "attendance_id": 31,
            "employee_id": 1,
            "attendance_date": "2024-04-03T18:30:00.000Z",
            "status": "Present"
        },
        {
            "attendance_id": 32,
            "employee_id": 2,
            "attendance_date": "2024-04-03T18:30:00.000Z",
            "status": "Present"
        },
        {
            "attendance_id": 33,
            "employee_id": 3,
            "attendance_date": "2024-04-03T18:30:00.000Z",
            "status": "Present"
        },
        {
            "attendance_id": 34,
            "employee_id": 4,
            "attendance_date": "2024-04-03T18:30:00.000Z",
            "status": "Absent"
        },
        {
            "attendance_id": 35,
            "employee_id": 5,
            "attendance_date": "2024-04-03T18:30:00.000Z",
            "status": "Present"
        },
        {
            "attendance_id": 36,
            "employee_id": 6,
            "attendance_date": "2024-04-03T18:30:00.000Z",
            "status": "Absent"
        },
        {
            "attendance_id": 37,
            "employee_id": 7,
            "attendance_date": "2024-04-03T18:30:00.000Z",
            "status": "Late"
        },
        {
            "attendance_id": 38,
            "employee_id": 8,
            "attendance_date": "2024-04-03T18:30:00.000Z",
            "status": "Present"
        },
        {
            "attendance_id": 39,
            "employee_id": 9,
            "attendance_date": "2024-04-03T18:30:00.000Z",
            "status": "Present"
        },
        {
            "attendance_id": 40,
            "employee_id": 10,
            "attendance_date": "2024-04-03T18:30:00.000Z",
            "status": "Present"
        },
        {
            "attendance_id": 41,
            "employee_id": 1,
            "attendance_date": "2024-04-04T18:30:00.000Z",
            "status": "Present"
        },
        {
            "attendance_id": 42,
            "employee_id": 2,
            "attendance_date": "2024-04-04T18:30:00.000Z",
            "status": "Absent"
        },
        {
            "attendance_id": 43,
            "employee_id": 3,
            "attendance_date": "2024-04-04T18:30:00.000Z",
            "status": "Present"
        },
        {
            "attendance_id": 44,
            "employee_id": 4,
            "attendance_date": "2024-04-04T18:30:00.000Z",
            "status": "Present"
        },
        {
            "attendance_id": 45,
            "employee_id": 5,
            "attendance_date": "2024-04-04T18:30:00.000Z",
            "status": "Present"
        },
        {
            "attendance_id": 46,
            "employee_id": 6,
            "attendance_date": "2024-04-04T18:30:00.000Z",
            "status": "Absent"
        },
        {
            "attendance_id": 47,
            "employee_id": 7,
            "attendance_date": "2024-04-04T18:30:00.000Z",
            "status": "Present"
        },
        {
            "attendance_id": 48,
            "employee_id": 8,
            "attendance_date": "2024-04-04T18:30:00.000Z",
            "status": "Late"
        },
        {
            "attendance_id": 49,
            "employee_id": 9,
            "attendance_date": "2024-04-04T18:30:00.000Z",
            "status": "Present"
        },
        {
            "attendance_id": 50,
            "employee_id": 10,
            "attendance_date": "2024-04-04T18:30:00.000Z",
            "status": "Absent"
        },
        {
            "attendance_id": 51,
            "employee_id": 1,
            "attendance_date": "2024-04-05T18:30:00.000Z",
            "status": "Absent"
        },
        {
            "attendance_id": 52,
            "employee_id": 2,
            "attendance_date": "2024-04-05T18:30:00.000Z",
            "status": "Present"
        },
        {
            "attendance_id": 53,
            "employee_id": 3,
            "attendance_date": "2024-04-05T18:30:00.000Z",
            "status": "Present"
        },
        {
            "attendance_id": 54,
            "employee_id": 4,
            "attendance_date": "2024-04-05T18:30:00.000Z",
            "status": "Present"
        },
        {
            "attendance_id": 55,
            "employee_id": 5,
            "attendance_date": "2024-04-05T18:30:00.000Z",
            "status": "Late"
        },
        {
            "attendance_id": 56,
            "employee_id": 6,
            "attendance_date": "2024-04-05T18:30:00.000Z",
            "status": "Absent"
        },
        {
            "attendance_id": 57,
            "employee_id": 7,
            "attendance_date": "2024-04-05T18:30:00.000Z",
            "status": "Present"
        },
        {
            "attendance_id": 58,
            "employee_id": 8,
            "attendance_date": "2024-04-05T18:30:00.000Z",
            "status": "Present"
        },
        {
            "attendance_id": 59,
            "employee_id": 9,
            "attendance_date": "2024-04-05T18:30:00.000Z",
            "status": "Present"
        },
        {
            "attendance_id": 60,
            "employee_id": 10,
            "attendance_date": "2024-04-05T18:30:00.000Z",
            "status": "Present"
        },
        {
            "attendance_id": 61,
            "employee_id": 1,
            "attendance_date": "2024-04-06T18:30:00.000Z",
            "status": "Present"
        },
        {
            "attendance_id": 62,
            "employee_id": 2,
            "attendance_date": "2024-04-06T18:30:00.000Z",
            "status": "Absent"
        },
        {
            "attendance_id": 63,
            "employee_id": 3,
            "attendance_date": "2024-04-06T18:30:00.000Z",
            "status": "Absent"
        },
        {
            "attendance_id": 64,
            "employee_id": 4,
            "attendance_date": "2024-04-06T18:30:00.000Z",
            "status": "Present"
        },
        {
            "attendance_id": 65,
            "employee_id": 5,
            "attendance_date": "2024-04-06T18:30:00.000Z",
            "status": "Present"
        },
        {
            "attendance_id": 66,
            "employee_id": 6,
            "attendance_date": "2024-04-06T18:30:00.000Z",
            "status": "Present"
        },
        {
            "attendance_id": 67,
            "employee_id": 7,
            "attendance_date": "2024-04-06T18:30:00.000Z",
            "status": "Absent"
        },
        {
            "attendance_id": 68,
            "employee_id": 8,
            "attendance_date": "2024-04-06T18:30:00.000Z",
            "status": "Present"
        },
        {
            "attendance_id": 69,
            "employee_id": 9,
            "attendance_date": "2024-04-06T18:30:00.000Z",
            "status": "Late"
        },
        {
            "attendance_id": 70,
            "employee_id": 10,
            "attendance_date": "2024-04-06T18:30:00.000Z",
            "status": "Absent"
        },
        {
            "attendance_id": 71,
            "employee_id": 1,
            "attendance_date": "2024-04-07T18:30:00.000Z",
            "status": "Present"
        },
        {
            "attendance_id": 72,
            "employee_id": 2,
            "attendance_date": "2024-04-07T18:30:00.000Z",
            "status": "Present"
        },
        {
            "attendance_id": 73,
            "employee_id": 3,
            "attendance_date": "2024-04-07T18:30:00.000Z",
            "status": "Absent"
        },
        {
            "attendance_id": 74,
            "employee_id": 4,
            "attendance_date": "2024-04-07T18:30:00.000Z",
            "status": "Present"
        },
        {
            "attendance_id": 75,
            "employee_id": 5,
            "attendance_date": "2024-04-07T18:30:00.000Z",
            "status": "Absent"
        },
        {
            "attendance_id": 76,
            "employee_id": 6,
            "attendance_date": "2024-04-07T18:30:00.000Z",
            "status": "Present"
        },
        {
            "attendance_id": 77,
            "employee_id": 7,
            "attendance_date": "2024-04-07T18:30:00.000Z",
            "status": "Present"
        },
        {
            "attendance_id": 78,
            "employee_id": 8,
            "attendance_date": "2024-04-07T18:30:00.000Z",
            "status": "Absent"
        },
        {
            "attendance_id": 79,
            "employee_id": 9,
            "attendance_date": "2024-04-07T18:30:00.000Z",
            "status": "Present"
        },
        {
            "attendance_id": 80,
            "employee_id": 10,
            "attendance_date": "2024-04-07T18:30:00.000Z",
            "status": "Present"
        },
        {
            "attendance_id": 81,
            "employee_id": 1,
            "attendance_date": "2024-04-08T18:30:00.000Z",
            "status": "Present"
        },
        {
            "attendance_id": 82,
            "employee_id": 2,
            "attendance_date": "2024-04-08T18:30:00.000Z",
            "status": "Absent"
        },
        {
            "attendance_id": 83,
            "employee_id": 3,
            "attendance_date": "2024-04-08T18:30:00.000Z",
            "status": "Present"
        },
        {
            "attendance_id": 84,
            "employee_id": 4,
            "attendance_date": "2024-04-08T18:30:00.000Z",
            "status": "Present"
        },
        {
            "attendance_id": 85,
            "employee_id": 5,
            "attendance_date": "2024-04-08T18:30:00.000Z",
            "status": "Late"
        },
        {
            "attendance_id": 86,
            "employee_id": 6,
            "attendance_date": "2024-04-08T18:30:00.000Z",
            "status": "Absent"
        },
        {
            "attendance_id": 87,
            "employee_id": 7,
            "attendance_date": "2024-04-08T18:30:00.000Z",
            "status": "Present"
        },
        {
            "attendance_id": 88,
            "employee_id": 8,
            "attendance_date": "2024-04-08T18:30:00.000Z",
            "status": "Present"
        },
        {
            "attendance_id": 89,
            "employee_id": 9,
            "attendance_date": "2024-04-08T18:30:00.000Z",
            "status": "Absent"
        },
        {
            "attendance_id": 90,
            "employee_id": 10,
            "attendance_date": "2024-04-08T18:30:00.000Z",
            "status": "Present"
        },
        {
            "attendance_id": 91,
            "employee_id": 1,
            "attendance_date": "2024-04-09T18:30:00.000Z",
            "status": "Present"
        },
        {
            "attendance_id": 92,
            "employee_id": 2,
            "attendance_date": "2024-04-09T18:30:00.000Z",
            "status": "Present"
        },
        {
            "attendance_id": 93,
            "employee_id": 3,
            "attendance_date": "2024-04-09T18:30:00.000Z",
            "status": "Absent"
        },
        {
            "attendance_id": 94,
            "employee_id": 4,
            "attendance_date": "2024-04-09T18:30:00.000Z",
            "status": "Present"
        },
        {
            "attendance_id": 95,
            "employee_id": 5,
            "attendance_date": "2024-04-09T18:30:00.000Z",
            "status": "Present"
        },
        {
            "attendance_id": 96,
            "employee_id": 6,
            "attendance_date": "2024-04-09T18:30:00.000Z",
            "status": "Absent"
        },
        {
            "attendance_id": 97,
            "employee_id": 7,
            "attendance_date": "2024-04-09T18:30:00.000Z",
            "status": "Present"
        },
        {
            "attendance_id": 98,
            "employee_id": 8,
            "attendance_date": "2024-04-09T18:30:00.000Z",
            "status": "Absent"
        },
        {
            "attendance_id": 99,
            "employee_id": 9,
            "attendance_date": "2024-04-09T18:30:00.000Z",
            "status": "Present"
        },
        {
            "attendance_id": 100,
            "employee_id": 10,
            "attendance_date": "2024-04-09T18:30:00.000Z",
            "status": "Present"
        },
        {
            "attendance_id": 101,
            "employee_id": 1,
            "attendance_date": "2024-04-10T18:30:00.000Z",
            "status": "Present"
        },
        {
            "attendance_id": 102,
            "employee_id": 2,
            "attendance_date": "2024-04-10T18:30:00.000Z",
            "status": "Absent"
        },
        {
            "attendance_id": 103,
            "employee_id": 3,
            "attendance_date": "2024-04-10T18:30:00.000Z",
            "status": "Present"
        },
        {
            "attendance_id": 104,
            "employee_id": 4,
            "attendance_date": "2024-04-10T18:30:00.000Z",
            "status": "Present"
        },
        {
            "attendance_id": 105,
            "employee_id": 5,
            "attendance_date": "2024-04-10T18:30:00.000Z",
            "status": "Present"
        },
        {
            "attendance_id": 106,
            "employee_id": 6,
            "attendance_date": "2024-04-10T18:30:00.000Z",
            "status": "Absent"
        },
        {
            "attendance_id": 107,
            "employee_id": 7,
            "attendance_date": "2024-04-10T18:30:00.000Z",
            "status": "Present"
        },
        {
            "attendance_id": 108,
            "employee_id": 8,
            "attendance_date": "2024-04-10T18:30:00.000Z",
            "status": "Present"
        },
        {
            "attendance_id": 109,
            "employee_id": 9,
            "attendance_date": "2024-04-10T18:30:00.000Z",
            "status": "Absent"
        },
        {
            "attendance_id": 110,
            "employee_id": 10,
            "attendance_date": "2024-04-10T18:30:00.000Z",
            "status": "Present"
        },
        {
            "attendance_id": 111,
            "employee_id": 1,
            "attendance_date": "2024-04-11T18:30:00.000Z",
            "status": "Present"
        },
        {
            "attendance_id": 112,
            "employee_id": 2,
            "attendance_date": "2024-04-11T18:30:00.000Z",
            "status": "Absent"
        },
        {
            "attendance_id": 113,
            "employee_id": 3,
            "attendance_date": "2024-04-11T18:30:00.000Z",
            "status": "Present"
        },
        {
            "attendance_id": 114,
            "employee_id": 4,
            "attendance_date": "2024-04-11T18:30:00.000Z",
            "status": "Present"
        },
        {
            "attendance_id": 115,
            "employee_id": 5,
            "attendance_date": "2024-04-11T18:30:00.000Z",
            "status": "Present"
        },
        {
            "attendance_id": 116,
            "employee_id": 6,
            "attendance_date": "2024-04-11T18:30:00.000Z",
            "status": "Absent"
        },
        {
            "attendance_id": 117,
            "employee_id": 7,
            "attendance_date": "2024-04-11T18:30:00.000Z",
            "status": "Present"
        },
        {
            "attendance_id": 118,
            "employee_id": 8,
            "attendance_date": "2024-04-11T18:30:00.000Z",
            "status": "Absent"
        },
        {
            "attendance_id": 119,
            "employee_id": 9,
            "attendance_date": "2024-04-11T18:30:00.000Z",
            "status": "Present"
        },
        {
            "attendance_id": 120,
            "employee_id": 10,
            "attendance_date": "2024-04-11T18:30:00.000Z",
            "status": "Present"
        },
        {
            "attendance_id": 121,
            "employee_id": 1,
            "attendance_date": "2024-04-12T18:30:00.000Z",
            "status": "Present"
        },
        {
            "attendance_id": 122,
            "employee_id": 2,
            "attendance_date": "2024-04-12T18:30:00.000Z",
            "status": "Absent"
        },
        {
            "attendance_id": 123,
            "employee_id": 3,
            "attendance_date": "2024-04-12T18:30:00.000Z",
            "status": "Present"
        },
        {
            "attendance_id": 124,
            "employee_id": 4,
            "attendance_date": "2024-04-12T18:30:00.000Z",
            "status": "Present"
        },
        {
            "attendance_id": 125,
            "employee_id": 5,
            "attendance_date": "2024-04-12T18:30:00.000Z",
            "status": "Present"
        },
        {
            "attendance_id": 126,
            "employee_id": 6,
            "attendance_date": "2024-04-12T18:30:00.000Z",
            "status": "Absent"
        },
        {
            "attendance_id": 127,
            "employee_id": 7,
            "attendance_date": "2024-04-12T18:30:00.000Z",
            "status": "Present"
        },
        {
            "attendance_id": 128,
            "employee_id": 8,
            "attendance_date": "2024-04-12T18:30:00.000Z",
            "status": "Absent"
        },
        {
            "attendance_id": 129,
            "employee_id": 9,
            "attendance_date": "2024-04-12T18:30:00.000Z",
            "status": "Present"
        },
        {
            "attendance_id": 130,
            "employee_id": 10,
            "attendance_date": "2024-04-12T18:30:00.000Z",
            "status": "Present"
        },
        {
            "attendance_id": 131,
            "employee_id": 1,
            "attendance_date": "2024-04-13T18:30:00.000Z",
            "status": "Absent"
        },
        {
            "attendance_id": 132,
            "employee_id": 2,
            "attendance_date": "2024-04-13T18:30:00.000Z",
            "status": "Present"
        },
        {
            "attendance_id": 133,
            "employee_id": 3,
            "attendance_date": "2024-04-13T18:30:00.000Z",
            "status": "Absent"
        },
        {
            "attendance_id": 134,
            "employee_id": 4,
            "attendance_date": "2024-04-13T18:30:00.000Z",
            "status": "Present"
        },
        {
            "attendance_id": 135,
            "employee_id": 5,
            "attendance_date": "2024-04-13T18:30:00.000Z",
            "status": "Present"
        },
        {
            "attendance_id": 136,
            "employee_id": 6,
            "attendance_date": "2024-04-13T18:30:00.000Z",
            "status": "Absent"
        },
        {
            "attendance_id": 137,
            "employee_id": 7,
            "attendance_date": "2024-04-13T18:30:00.000Z",
            "status": "Present"
        },
        {
            "attendance_id": 138,
            "employee_id": 8,
            "attendance_date": "2024-04-13T18:30:00.000Z",
            "status": "Present"
        },
        {
            "attendance_id": 139,
            "employee_id": 9,
            "attendance_date": "2024-04-13T18:30:00.000Z",
            "status": "Present"
        },
        {
            "attendance_id": 140,
            "employee_id": 10,
            "attendance_date": "2024-04-13T18:30:00.000Z",
            "status": "Present"
        },
        {
            "attendance_id": 141,
            "employee_id": 1,
            "attendance_date": "2024-04-14T18:30:00.000Z",
            "status": "Present"
        },
        {
            "attendance_id": 142,
            "employee_id": 2,
            "attendance_date": "2024-04-14T18:30:00.000Z",
            "status": "Absent"
        },
        {
            "attendance_id": 143,
            "employee_id": 3,
            "attendance_date": "2024-04-14T18:30:00.000Z",
            "status": "Absent"
        },
        {
            "attendance_id": 144,
            "employee_id": 4,
            "attendance_date": "2024-04-14T18:30:00.000Z",
            "status": "Present"
        },
        {
            "attendance_id": 145,
            "employee_id": 5,
            "attendance_date": "2024-04-14T18:30:00.000Z",
            "status": "Present"
        },
        {
            "attendance_id": 146,
            "employee_id": 6,
            "attendance_date": "2024-04-14T18:30:00.000Z",
            "status": "Absent"
        },
        {
            "attendance_id": 147,
            "employee_id": 7,
            "attendance_date": "2024-04-14T18:30:00.000Z",
            "status": "Present"
        },
        {
            "attendance_id": 148,
            "employee_id": 8,
            "attendance_date": "2024-04-14T18:30:00.000Z",
            "status": "Absent"
        },
        {
            "attendance_id": 149,
            "employee_id": 9,
            "attendance_date": "2024-04-14T18:30:00.000Z",
            "status": "Present"
        },
        {
            "attendance_id": 150,
            "employee_id": 10,
            "attendance_date": "2024-04-14T18:30:00.000Z",
            "status": "Present"
        },
        {
            "attendance_id": 151,
            "employee_id": 1,
            "attendance_date": "2024-04-15T18:30:00.000Z",
            "status": "Present"
        },
        {
            "attendance_id": 152,
            "employee_id": 2,
            "attendance_date": "2024-04-15T18:30:00.000Z",
            "status": "Present"
        },
        {
            "attendance_id": 153,
            "employee_id": 3,
            "attendance_date": "2024-04-15T18:30:00.000Z",
            "status": "Absent"
        },
        {
            "attendance_id": 154,
            "employee_id": 4,
            "attendance_date": "2024-04-15T18:30:00.000Z",
            "status": "Present"
        },
        {
            "attendance_id": 155,
            "employee_id": 5,
            "attendance_date": "2024-04-15T18:30:00.000Z",
            "status": "Present"
        },
        {
            "attendance_id": 156,
            "employee_id": 6,
            "attendance_date": "2024-04-15T18:30:00.000Z",
            "status": "Absent"
        },
        {
            "attendance_id": 157,
            "employee_id": 7,
            "attendance_date": "2024-04-15T18:30:00.000Z",
            "status": "Present"
        },
        {
            "attendance_id": 158,
            "employee_id": 8,
            "attendance_date": "2024-04-15T18:30:00.000Z",
            "status": "Present"
        },
        {
            "attendance_id": 159,
            "employee_id": 9,
            "attendance_date": "2024-04-15T18:30:00.000Z",
            "status": "Absent"
        },
        {
            "attendance_id": 160,
            "employee_id": 10,
            "attendance_date": "2024-04-15T18:30:00.000Z",
            "status": "Present"
        },
        {
            "attendance_id": 161,
            "employee_id": 1,
            "attendance_date": "2024-04-16T18:30:00.000Z",
            "status": "Present"
        },
        {
            "attendance_id": 162,
            "employee_id": 2,
            "attendance_date": "2024-04-16T18:30:00.000Z",
            "status": "Absent"
        },
        {
            "attendance_id": 163,
            "employee_id": 3,
            "attendance_date": "2024-04-16T18:30:00.000Z",
            "status": "Present"
        },
        {
            "attendance_id": 164,
            "employee_id": 4,
            "attendance_date": "2024-04-16T18:30:00.000Z",
            "status": "Present"
        },
        {
            "attendance_id": 165,
            "employee_id": 5,
            "attendance_date": "2024-04-16T18:30:00.000Z",
            "status": "Present"
        },
        {
            "attendance_id": 166,
            "employee_id": 6,
            "attendance_date": "2024-04-16T18:30:00.000Z",
            "status": "Absent"
        },
        {
            "attendance_id": 167,
            "employee_id": 7,
            "attendance_date": "2024-04-16T18:30:00.000Z",
            "status": "Present"
        },
        {
            "attendance_id": 168,
            "employee_id": 8,
            "attendance_date": "2024-04-16T18:30:00.000Z",
            "status": "Absent"
        },
        {
            "attendance_id": 169,
            "employee_id": 9,
            "attendance_date": "2024-04-16T18:30:00.000Z",
            "status": "Present"
        },
        {
            "attendance_id": 170,
            "employee_id": 10,
            "attendance_date": "2024-04-16T18:30:00.000Z",
            "status": "Present"
        },
        {
            "attendance_id": 171,
            "employee_id": 1,
            "attendance_date": "2024-04-17T18:30:00.000Z",
            "status": "Present"
        },
        {
            "attendance_id": 172,
            "employee_id": 2,
            "attendance_date": "2024-04-17T18:30:00.000Z",
            "status": "Absent"
        },
        {
            "attendance_id": 173,
            "employee_id": 3,
            "attendance_date": "2024-04-17T18:30:00.000Z",
            "status": "Present"
        },
        {
            "attendance_id": 174,
            "employee_id": 4,
            "attendance_date": "2024-04-17T18:30:00.000Z",
            "status": "Present"
        },
        {
            "attendance_id": 175,
            "employee_id": 5,
            "attendance_date": "2024-04-17T18:30:00.000Z",
            "status": "Present"
        },
        {
            "attendance_id": 176,
            "employee_id": 6,
            "attendance_date": "2024-04-17T18:30:00.000Z",
            "status": "Absent"
        },
        {
            "attendance_id": 177,
            "employee_id": 7,
            "attendance_date": "2024-04-17T18:30:00.000Z",
            "status": "Present"
        },
        {
            "attendance_id": 178,
            "employee_id": 8,
            "attendance_date": "2024-04-17T18:30:00.000Z",
            "status": "Absent"
        },
        {
            "attendance_id": 179,
            "employee_id": 9,
            "attendance_date": "2024-04-17T18:30:00.000Z",
            "status": "Present"
        },
        {
            "attendance_id": 180,
            "employee_id": 10,
            "attendance_date": "2024-04-17T18:30:00.000Z",
            "status": "Present"
        },
        {
            "attendance_id": 181,
            "employee_id": 1,
            "attendance_date": "2024-04-18T18:30:00.000Z",
            "status": "Absent"
        },
        {
            "attendance_id": 182,
            "employee_id": 2,
            "attendance_date": "2024-04-18T18:30:00.000Z",
            "status": "Present"
        },
        {
            "attendance_id": 183,
            "employee_id": 3,
            "attendance_date": "2024-04-18T18:30:00.000Z",
            "status": "Absent"
        },
        {
            "attendance_id": 184,
            "employee_id": 4,
            "attendance_date": "2024-04-18T18:30:00.000Z",
            "status": "Present"
        },
        {
            "attendance_id": 185,
            "employee_id": 5,
            "attendance_date": "2024-04-18T18:30:00.000Z",
            "status": "Present"
        },
        {
            "attendance_id": 186,
            "employee_id": 6,
            "attendance_date": "2024-04-18T18:30:00.000Z",
            "status": "Absent"
        },
        {
            "attendance_id": 187,
            "employee_id": 7,
            "attendance_date": "2024-04-18T18:30:00.000Z",
            "status": "Present"
        },
        {
            "attendance_id": 188,
            "employee_id": 8,
            "attendance_date": "2024-04-18T18:30:00.000Z",
            "status": "Present"
        },
        {
            "attendance_id": 189,
            "employee_id": 9,
            "attendance_date": "2024-04-18T18:30:00.000Z",
            "status": "Present"
        },
        {
            "attendance_id": 190,
            "employee_id": 10,
            "attendance_date": "2024-04-18T18:30:00.000Z",
            "status": "Present"
        },
        {
            "attendance_id": 191,
            "employee_id": 1,
            "attendance_date": "2024-04-19T18:30:00.000Z",
            "status": "Present"
        },
        {
            "attendance_id": 192,
            "employee_id": 2,
            "attendance_date": "2024-04-19T18:30:00.000Z",
            "status": "Present"
        },
        {
            "attendance_id": 193,
            "employee_id": 3,
            "attendance_date": "2024-04-19T18:30:00.000Z",
            "status": "Absent"
        },
        {
            "attendance_id": 194,
            "employee_id": 4,
            "attendance_date": "2024-04-19T18:30:00.000Z",
            "status": "Present"
        },
        {
            "attendance_id": 195,
            "employee_id": 5,
            "attendance_date": "2024-04-19T18:30:00.000Z",
            "status": "Present"
        },
        {
            "attendance_id": 196,
            "employee_id": 6,
            "attendance_date": "2024-04-19T18:30:00.000Z",
            "status": "Absent"
        },
        {
            "attendance_id": 197,
            "employee_id": 7,
            "attendance_date": "2024-04-19T18:30:00.000Z",
            "status": "Present"
        },
        {
            "attendance_id": 198,
            "employee_id": 8,
            "attendance_date": "2024-04-19T18:30:00.000Z",
            "status": "Present"
        },
        {
            "attendance_id": 199,
            "employee_id": 9,
            "attendance_date": "2024-04-19T18:30:00.000Z",
            "status": "Absent"
        },
        {
            "attendance_id": 200,
            "employee_id": 10,
            "attendance_date": "2024-04-19T18:30:00.000Z",
            "status": "Present"
        },
        {
            "attendance_id": 201,
            "employee_id": 1,
            "attendance_date": "2024-04-20T18:30:00.000Z",
            "status": "Present"
        },
        {
            "attendance_id": 202,
            "employee_id": 2,
            "attendance_date": "2024-04-20T18:30:00.000Z",
            "status": "Present"
        },
        {
            "attendance_id": 203,
            "employee_id": 3,
            "attendance_date": "2024-04-20T18:30:00.000Z",
            "status": "Absent"
        },
        {
            "attendance_id": 204,
            "employee_id": 4,
            "attendance_date": "2024-04-20T18:30:00.000Z",
            "status": "Present"
        },
        {
            "attendance_id": 205,
            "employee_id": 5,
            "attendance_date": "2024-04-20T18:30:00.000Z",
            "status": "Present"
        },
        {
            "attendance_id": 206,
            "employee_id": 6,
            "attendance_date": "2024-04-20T18:30:00.000Z",
            "status": "Absent"
        },
        {
            "attendance_id": 207,
            "employee_id": 7,
            "attendance_date": "2024-04-20T18:30:00.000Z",
            "status": "Present"
        },
        {
            "attendance_id": 208,
            "employee_id": 8,
            "attendance_date": "2024-04-20T18:30:00.000Z",
            "status": "Present"
        },
        {
            "attendance_id": 209,
            "employee_id": 9,
            "attendance_date": "2024-04-20T18:30:00.000Z",
            "status": "Absent"
        },
        {
            "attendance_id": 210,
            "employee_id": 10,
            "attendance_date": "2024-04-20T18:30:00.000Z",
            "status": "Present"
        },
        {
            "attendance_id": 211,
            "employee_id": 1,
            "attendance_date": "2024-04-21T18:30:00.000Z",
            "status": "Present"
        },
        {
            "attendance_id": 212,
            "employee_id": 2,
            "attendance_date": "2024-04-21T18:30:00.000Z",
            "status": "Absent"
        },
        {
            "attendance_id": 213,
            "employee_id": 3,
            "attendance_date": "2024-04-21T18:30:00.000Z",
            "status": "Present"
        },
        {
            "attendance_id": 214,
            "employee_id": 4,
            "attendance_date": "2024-04-21T18:30:00.000Z",
            "status": "Present"
        },
        {
            "attendance_id": 215,
            "employee_id": 5,
            "attendance_date": "2024-04-21T18:30:00.000Z",
            "status": "Present"
        },
        {
            "attendance_id": 216,
            "employee_id": 6,
            "attendance_date": "2024-04-21T18:30:00.000Z",
            "status": "Absent"
        },
        {
            "attendance_id": 217,
            "employee_id": 7,
            "attendance_date": "2024-04-21T18:30:00.000Z",
            "status": "Present"
        },
        {
            "attendance_id": 218,
            "employee_id": 8,
            "attendance_date": "2024-04-21T18:30:00.000Z",
            "status": "Absent"
        },
        {
            "attendance_id": 219,
            "employee_id": 9,
            "attendance_date": "2024-04-21T18:30:00.000Z",
            "status": "Present"
        },
        {
            "attendance_id": 220,
            "employee_id": 10,
            "attendance_date": "2024-04-21T18:30:00.000Z",
            "status": "Present"
        },
        {
            "attendance_id": 221,
            "employee_id": 1,
            "attendance_date": "2024-04-22T18:30:00.000Z",
            "status": "Present"
        },
        {
            "attendance_id": 222,
            "employee_id": 2,
            "attendance_date": "2024-04-22T18:30:00.000Z",
            "status": "Absent"
        },
        {
            "attendance_id": 223,
            "employee_id": 3,
            "attendance_date": "2024-04-22T18:30:00.000Z",
            "status": "Present"
        },
        {
            "attendance_id": 224,
            "employee_id": 4,
            "attendance_date": "2024-04-22T18:30:00.000Z",
            "status": "Present"
        },
        {
            "attendance_id": 225,
            "employee_id": 5,
            "attendance_date": "2024-04-22T18:30:00.000Z",
            "status": "Present"
        },
        {
            "attendance_id": 226,
            "employee_id": 6,
            "attendance_date": "2024-04-22T18:30:00.000Z",
            "status": "Absent"
        },
        {
            "attendance_id": 227,
            "employee_id": 7,
            "attendance_date": "2024-04-22T18:30:00.000Z",
            "status": "Present"
        },
        {
            "attendance_id": 228,
            "employee_id": 8,
            "attendance_date": "2024-04-22T18:30:00.000Z",
            "status": "Absent"
        },
        {
            "attendance_id": 229,
            "employee_id": 9,
            "attendance_date": "2024-04-22T18:30:00.000Z",
            "status": "Present"
        },
        {
            "attendance_id": 230,
            "employee_id": 10,
            "attendance_date": "2024-04-22T18:30:00.000Z",
            "status": "Present"
        },
        {
            "attendance_id": 231,
            "employee_id": 1,
            "attendance_date": "2024-04-23T18:30:00.000Z",
            "status": "Absent"
        },
        {
            "attendance_id": 232,
            "employee_id": 2,
            "attendance_date": "2024-04-23T18:30:00.000Z",
            "status": "Present"
        },
        {
            "attendance_id": 233,
            "employee_id": 3,
            "attendance_date": "2024-04-23T18:30:00.000Z",
            "status": "Absent"
        },
        {
            "attendance_id": 234,
            "employee_id": 4,
            "attendance_date": "2024-04-23T18:30:00.000Z",
            "status": "Present"
        },
        {
            "attendance_id": 235,
            "employee_id": 5,
            "attendance_date": "2024-04-23T18:30:00.000Z",
            "status": "Present"
        },
        {
            "attendance_id": 236,
            "employee_id": 6,
            "attendance_date": "2024-04-23T18:30:00.000Z",
            "status": "Absent"
        },
        {
            "attendance_id": 237,
            "employee_id": 7,
            "attendance_date": "2024-04-23T18:30:00.000Z",
            "status": "Present"
        },
        {
            "attendance_id": 238,
            "employee_id": 8,
            "attendance_date": "2024-04-23T18:30:00.000Z",
            "status": "Present"
        },
        {
            "attendance_id": 239,
            "employee_id": 9,
            "attendance_date": "2024-04-23T18:30:00.000Z",
            "status": "Present"
        },
        {
            "attendance_id": 240,
            "employee_id": 10,
            "attendance_date": "2024-04-23T18:30:00.000Z",
            "status": "Present"
        },
        {
            "attendance_id": 241,
            "employee_id": 1,
            "attendance_date": "2024-04-24T18:30:00.000Z",
            "status": "Present"
        },
        {
            "attendance_id": 242,
            "employee_id": 2,
            "attendance_date": "2024-04-24T18:30:00.000Z",
            "status": "Absent"
        },
        {
            "attendance_id": 243,
            "employee_id": 3,
            "attendance_date": "2024-04-24T18:30:00.000Z",
            "status": "Absent"
        },
        {
            "attendance_id": 244,
            "employee_id": 4,
            "attendance_date": "2024-04-24T18:30:00.000Z",
            "status": "Present"
        },
        {
            "attendance_id": 245,
            "employee_id": 5,
            "attendance_date": "2024-04-24T18:30:00.000Z",
            "status": "Present"
        },
        {
            "attendance_id": 246,
            "employee_id": 6,
            "attendance_date": "2024-04-24T18:30:00.000Z",
            "status": "Absent"
        },
        {
            "attendance_id": 247,
            "employee_id": 7,
            "attendance_date": "2024-04-24T18:30:00.000Z",
            "status": "Present"
        },
        {
            "attendance_id": 248,
            "employee_id": 8,
            "attendance_date": "2024-04-24T18:30:00.000Z",
            "status": "Present"
        },
        {
            "attendance_id": 249,
            "employee_id": 9,
            "attendance_date": "2024-04-24T18:30:00.000Z",
            "status": "Absent"
        },
        {
            "attendance_id": 250,
            "employee_id": 10,
            "attendance_date": "2024-04-24T18:30:00.000Z",
            "status": "Present"
        },
        {
            "attendance_id": 251,
            "employee_id": 1,
            "attendance_date": "2024-04-25T18:30:00.000Z",
            "status": "Present"
        },
        {
            "attendance_id": 252,
            "employee_id": 2,
            "attendance_date": "2024-04-25T18:30:00.000Z",
            "status": "Present"
        },
        {
            "attendance_id": 253,
            "employee_id": 3,
            "attendance_date": "2024-04-25T18:30:00.000Z",
            "status": "Absent"
        },
        {
            "attendance_id": 254,
            "employee_id": 4,
            "attendance_date": "2024-04-25T18:30:00.000Z",
            "status": "Present"
        },
        {
            "attendance_id": 255,
            "employee_id": 5,
            "attendance_date": "2024-04-25T18:30:00.000Z",
            "status": "Present"
        },
        {
            "attendance_id": 256,
            "employee_id": 6,
            "attendance_date": "2024-04-25T18:30:00.000Z",
            "status": "Absent"
        },
        {
            "attendance_id": 257,
            "employee_id": 7,
            "attendance_date": "2024-04-25T18:30:00.000Z",
            "status": "Present"
        },
        {
            "attendance_id": 258,
            "employee_id": 8,
            "attendance_date": "2024-04-25T18:30:00.000Z",
            "status": "Present"
        },
        {
            "attendance_id": 259,
            "employee_id": 9,
            "attendance_date": "2024-04-25T18:30:00.000Z",
            "status": "Absent"
        },
        {
            "attendance_id": 260,
            "employee_id": 10,
            "attendance_date": "2024-04-25T18:30:00.000Z",
            "status": "Present"
        },
        {
            "attendance_id": 261,
            "employee_id": 1,
            "attendance_date": "2024-04-26T18:30:00.000Z",
            "status": "Present"
        },
        {
            "attendance_id": 262,
            "employee_id": 2,
            "attendance_date": "2024-04-26T18:30:00.000Z",
            "status": "Present"
        },
        {
            "attendance_id": 263,
            "employee_id": 3,
            "attendance_date": "2024-04-26T18:30:00.000Z",
            "status": "Absent"
        },
        {
            "attendance_id": 264,
            "employee_id": 4,
            "attendance_date": "2024-04-26T18:30:00.000Z",
            "status": "Present"
        },
        {
            "attendance_id": 265,
            "employee_id": 5,
            "attendance_date": "2024-04-26T18:30:00.000Z",
            "status": "Present"
        },
        {
            "attendance_id": 266,
            "employee_id": 6,
            "attendance_date": "2024-04-26T18:30:00.000Z",
            "status": "Absent"
        },
        {
            "attendance_id": 267,
            "employee_id": 7,
            "attendance_date": "2024-04-26T18:30:00.000Z",
            "status": "Present"
        },
        {
            "attendance_id": 268,
            "employee_id": 8,
            "attendance_date": "2024-04-26T18:30:00.000Z",
            "status": "Present"
        },
        {
            "attendance_id": 269,
            "employee_id": 9,
            "attendance_date": "2024-04-26T18:30:00.000Z",
            "status": "Absent"
        },
        {
            "attendance_id": 270,
            "employee_id": 10,
            "attendance_date": "2024-04-26T18:30:00.000Z",
            "status": "Present"
        },
        {
            "attendance_id": 271,
            "employee_id": 1,
            "attendance_date": "2024-04-27T18:30:00.000Z",
            "status": "Present"
        },
        {
            "attendance_id": 272,
            "employee_id": 2,
            "attendance_date": "2024-04-27T18:30:00.000Z",
            "status": "Absent"
        },
        {
            "attendance_id": 273,
            "employee_id": 3,
            "attendance_date": "2024-04-27T18:30:00.000Z",
            "status": "Present"
        },
        {
            "attendance_id": 274,
            "employee_id": 4,
            "attendance_date": "2024-04-27T18:30:00.000Z",
            "status": "Present"
        },
        {
            "attendance_id": 275,
            "employee_id": 5,
            "attendance_date": "2024-04-27T18:30:00.000Z",
            "status": "Present"
        },
        {
            "attendance_id": 276,
            "employee_id": 6,
            "attendance_date": "2024-04-27T18:30:00.000Z",
            "status": "Absent"
        },
        {
            "attendance_id": 277,
            "employee_id": 7,
            "attendance_date": "2024-04-27T18:30:00.000Z",
            "status": "Present"
        },
        {
            "attendance_id": 278,
            "employee_id": 8,
            "attendance_date": "2024-04-27T18:30:00.000Z",
            "status": "Absent"
        },
        {
            "attendance_id": 279,
            "employee_id": 9,
            "attendance_date": "2024-04-27T18:30:00.000Z",
            "status": "Present"
        },
        {
            "attendance_id": 280,
            "employee_id": 10,
            "attendance_date": "2024-04-27T18:30:00.000Z",
            "status": "Present"
        },
        {
            "attendance_id": 281,
            "employee_id": 1,
            "attendance_date": "2024-04-28T18:30:00.000Z",
            "status": "Present"
        },
        {
            "attendance_id": 282,
            "employee_id": 2,
            "attendance_date": "2024-04-28T18:30:00.000Z",
            "status": "Absent"
        },
        {
            "attendance_id": 283,
            "employee_id": 3,
            "attendance_date": "2024-04-28T18:30:00.000Z",
            "status": "Present"
        },
        {
            "attendance_id": 284,
            "employee_id": 4,
            "attendance_date": "2024-04-28T18:30:00.000Z",
            "status": "Present"
        },
        {
            "attendance_id": 285,
            "employee_id": 5,
            "attendance_date": "2024-04-28T18:30:00.000Z",
            "status": "Present"
        },
        {
            "attendance_id": 286,
            "employee_id": 6,
            "attendance_date": "2024-04-28T18:30:00.000Z",
            "status": "Absent"
        },
        {
            "attendance_id": 287,
            "employee_id": 7,
            "attendance_date": "2024-04-28T18:30:00.000Z",
            "status": "Present"
        },
        {
            "attendance_id": 288,
            "employee_id": 8,
            "attendance_date": "2024-04-28T18:30:00.000Z",
            "status": "Absent"
        },
        {
            "attendance_id": 289,
            "employee_id": 9,
            "attendance_date": "2024-04-28T18:30:00.000Z",
            "status": "Present"
        },
        {
            "attendance_id": 290,
            "employee_id": 10,
            "attendance_date": "2024-04-28T18:30:00.000Z",
            "status": "Present"
        },
        {
            "attendance_id": 291,
            "employee_id": 1,
            "attendance_date": "2024-04-29T18:30:00.000Z",
            "status": "Absent"
        },
        {
            "attendance_id": 292,
            "employee_id": 2,
            "attendance_date": "2024-04-29T18:30:00.000Z",
            "status": "Present"
        },
        {
            "attendance_id": 293,
            "employee_id": 3,
            "attendance_date": "2024-04-29T18:30:00.000Z",
            "status": "Absent"
        },
        {
            "attendance_id": 294,
            "employee_id": 4,
            "attendance_date": "2024-04-29T18:30:00.000Z",
            "status": "Present"
        },
        {
            "attendance_id": 295,
            "employee_id": 5,
            "attendance_date": "2024-04-29T18:30:00.000Z",
            "status": "Present"
        },
        {
            "attendance_id": 296,
            "employee_id": 6,
            "attendance_date": "2024-04-29T18:30:00.000Z",
            "status": "Absent"
        },
        {
            "attendance_id": 297,
            "employee_id": 7,
            "attendance_date": "2024-04-29T18:30:00.000Z",
            "status": "Present"
        },
        {
            "attendance_id": 298,
            "employee_id": 8,
            "attendance_date": "2024-04-29T18:30:00.000Z",
            "status": "Present"
        },
        {
            "attendance_id": 299,
            "employee_id": 9,
            "attendance_date": "2024-04-29T18:30:00.000Z",
            "status": "Present"
        },
        {
            "attendance_id": 300,
            "employee_id": 10,
            "attendance_date": "2024-04-29T18:30:00.000Z",
            "status": "Present"
        },
        {
            "attendance_id": 301,
            "employee_id": 1,
            "attendance_date": "2024-04-30T18:30:00.000Z",
            "status": "Present"
        },
        {
            "attendance_id": 302,
            "employee_id": 2,
            "attendance_date": "2024-04-30T18:30:00.000Z",
            "status": "Present"
        },
        {
            "attendance_id": 303,
            "employee_id": 3,
            "attendance_date": "2024-04-30T18:30:00.000Z",
            "status": "Absent"
        },
        {
            "attendance_id": 304,
            "employee_id": 4,
            "attendance_date": "2024-04-30T18:30:00.000Z",
            "status": "Present"
        },
        {
            "attendance_id": 305,
            "employee_id": 5,
            "attendance_date": "2024-04-30T18:30:00.000Z",
            "status": "Present"
        },
        {
            "attendance_id": 306,
            "employee_id": 6,
            "attendance_date": "2024-04-30T18:30:00.000Z",
            "status": "Absent"
        },
        {
            "attendance_id": 307,
            "employee_id": 7,
            "attendance_date": "2024-04-30T18:30:00.000Z",
            "status": "Present"
        },
        {
            "attendance_id": 308,
            "employee_id": 8,
            "attendance_date": "2024-04-30T18:30:00.000Z",
            "status": "Present"
        },
        {
            "attendance_id": 309,
            "employee_id": 9,
            "attendance_date": "2024-04-30T18:30:00.000Z",
            "status": "Absent"
        },
        {
            "attendance_id": 310,
            "employee_id": 10,
            "attendance_date": "2024-04-30T18:30:00.000Z",
            "status": "Present"
        },
        {
            "attendance_id": 311,
            "employee_id": 1,
            "attendance_date": "2024-05-01T18:30:00.000Z",
            "status": "Present"
        },
        {
            "attendance_id": 312,
            "employee_id": 2,
            "attendance_date": "2024-05-01T18:30:00.000Z",
            "status": "Absent"
        },
        {
            "attendance_id": 313,
            "employee_id": 3,
            "attendance_date": "2024-05-01T18:30:00.000Z",
            "status": "Present"
        },
        {
            "attendance_id": 314,
            "employee_id": 4,
            "attendance_date": "2024-05-01T18:30:00.000Z",
            "status": "Present"
        },
        {
            "attendance_id": 315,
            "employee_id": 5,
            "attendance_date": "2024-05-01T18:30:00.000Z",
            "status": "Present"
        },
        {
            "attendance_id": 316,
            "employee_id": 6,
            "attendance_date": "2024-05-01T18:30:00.000Z",
            "status": "Absent"
        },
        {
            "attendance_id": 317,
            "employee_id": 7,
            "attendance_date": "2024-05-01T18:30:00.000Z",
            "status": "Present"
        },
        {
            "attendance_id": 318,
            "employee_id": 8,
            "attendance_date": "2024-05-01T18:30:00.000Z",
            "status": "Absent"
        },
        {
            "attendance_id": 319,
            "employee_id": 9,
            "attendance_date": "2024-05-01T18:30:00.000Z",
            "status": "Present"
        },
        {
            "attendance_id": 320,
            "employee_id": 10,
            "attendance_date": "2024-05-01T18:30:00.000Z",
            "status": "Present"
        },
        {
            "attendance_id": 321,
            "employee_id": 1,
            "attendance_date": "2024-05-02T18:30:00.000Z",
            "status": "Present"
        },
        {
            "attendance_id": 322,
            "employee_id": 2,
            "attendance_date": "2024-05-02T18:30:00.000Z",
            "status": "Absent"
        },
        {
            "attendance_id": 323,
            "employee_id": 3,
            "attendance_date": "2024-05-02T18:30:00.000Z",
            "status": "Present"
        },
        {
            "attendance_id": 324,
            "employee_id": 4,
            "attendance_date": "2024-05-02T18:30:00.000Z",
            "status": "Present"
        },
        {
            "attendance_id": 325,
            "employee_id": 5,
            "attendance_date": "2024-05-02T18:30:00.000Z",
            "status": "Present"
        },
        {
            "attendance_id": 326,
            "employee_id": 6,
            "attendance_date": "2024-05-02T18:30:00.000Z",
            "status": "Absent"
        },
        {
            "attendance_id": 327,
            "employee_id": 7,
            "attendance_date": "2024-05-02T18:30:00.000Z",
            "status": "Present"
        },
        {
            "attendance_id": 328,
            "employee_id": 8,
            "attendance_date": "2024-05-02T18:30:00.000Z",
            "status": "Present"
        },
        {
            "attendance_id": 329,
            "employee_id": 9,
            "attendance_date": "2024-05-02T18:30:00.000Z",
            "status": "Absent"
        },
        {
            "attendance_id": 330,
            "employee_id": 10,
            "attendance_date": "2024-05-02T18:30:00.000Z",
            "status": "Present"
        },
        {
            "attendance_id": 331,
            "employee_id": 1,
            "attendance_date": "2024-05-03T18:30:00.000Z",
            "status": "Present"
        },
        {
            "attendance_id": 332,
            "employee_id": 2,
            "attendance_date": "2024-05-03T18:30:00.000Z",
            "status": "Absent"
        },
        {
            "attendance_id": 333,
            "employee_id": 3,
            "attendance_date": "2024-05-03T18:30:00.000Z",
            "status": "Present"
        },
        {
            "attendance_id": 334,
            "employee_id": 4,
            "attendance_date": "2024-05-03T18:30:00.000Z",
            "status": "Present"
        },
        {
            "attendance_id": 335,
            "employee_id": 5,
            "attendance_date": "2024-05-03T18:30:00.000Z",
            "status": "Present"
        },
        {
            "attendance_id": 336,
            "employee_id": 6,
            "attendance_date": "2024-05-03T18:30:00.000Z",
            "status": "Absent"
        },
        {
            "attendance_id": 337,
            "employee_id": 7,
            "attendance_date": "2024-05-03T18:30:00.000Z",
            "status": "Present"
        },
        {
            "attendance_id": 338,
            "employee_id": 8,
            "attendance_date": "2024-05-03T18:30:00.000Z",
            "status": "Absent"
        },
        {
            "attendance_id": 339,
            "employee_id": 9,
            "attendance_date": "2024-05-03T18:30:00.000Z",
            "status": "Present"
        },
        {
            "attendance_id": 340,
            "employee_id": 10,
            "attendance_date": "2024-05-03T18:30:00.000Z",
            "status": "Present"
        },
        {
            "attendance_id": 341,
            "employee_id": 1,
            "attendance_date": "2024-05-04T18:30:00.000Z",
            "status": "Present"
        },
        {
            "attendance_id": 342,
            "employee_id": 2,
            "attendance_date": "2024-05-04T18:30:00.000Z",
            "status": "Absent"
        },
        {
            "attendance_id": 343,
            "employee_id": 3,
            "attendance_date": "2024-05-04T18:30:00.000Z",
            "status": "Present"
        },
        {
            "attendance_id": 344,
            "employee_id": 4,
            "attendance_date": "2024-05-04T18:30:00.000Z",
            "status": "Present"
        },
        {
            "attendance_id": 345,
            "employee_id": 5,
            "attendance_date": "2024-05-04T18:30:00.000Z",
            "status": "Present"
        },
        {
            "attendance_id": 346,
            "employee_id": 6,
            "attendance_date": "2024-05-04T18:30:00.000Z",
            "status": "Absent"
        },
        {
            "attendance_id": 347,
            "employee_id": 7,
            "attendance_date": "2024-05-04T18:30:00.000Z",
            "status": "Present"
        },
        {
            "attendance_id": 348,
            "employee_id": 8,
            "attendance_date": "2024-05-04T18:30:00.000Z",
            "status": "Absent"
        },
        {
            "attendance_id": 349,
            "employee_id": 9,
            "attendance_date": "2024-05-04T18:30:00.000Z",
            "status": "Present"
        },
        {
            "attendance_id": 350,
            "employee_id": 10,
            "attendance_date": "2024-05-04T18:30:00.000Z",
            "status": "Present"
        },
        {
            "attendance_id": 351,
            "employee_id": 1,
            "attendance_date": "2024-05-05T18:30:00.000Z",
            "status": "Absent"
        },
        {
            "attendance_id": 352,
            "employee_id": 2,
            "attendance_date": "2024-05-05T18:30:00.000Z",
            "status": "Present"
        },
        {
            "attendance_id": 353,
            "employee_id": 3,
            "attendance_date": "2024-05-05T18:30:00.000Z",
            "status": "Absent"
        },
        {
            "attendance_id": 354,
            "employee_id": 4,
            "attendance_date": "2024-05-05T18:30:00.000Z",
            "status": "Present"
        },
        {
            "attendance_id": 355,
            "employee_id": 5,
            "attendance_date": "2024-05-05T18:30:00.000Z",
            "status": "Present"
        },
        {
            "attendance_id": 356,
            "employee_id": 6,
            "attendance_date": "2024-05-05T18:30:00.000Z",
            "status": "Absent"
        },
        {
            "attendance_id": 357,
            "employee_id": 7,
            "attendance_date": "2024-05-05T18:30:00.000Z",
            "status": "Present"
        },
        {
            "attendance_id": 358,
            "employee_id": 8,
            "attendance_date": "2024-05-05T18:30:00.000Z",
            "status": "Present"
        },
        {
            "attendance_id": 359,
            "employee_id": 9,
            "attendance_date": "2024-05-05T18:30:00.000Z",
            "status": "Present"
        },
        {
            "attendance_id": 360,
            "employee_id": 10,
            "attendance_date": "2024-05-05T18:30:00.000Z",
            "status": "Present"
        },
        {
            "attendance_id": 361,
            "employee_id": 1,
            "attendance_date": "2024-05-06T18:30:00.000Z",
            "status": "Present"
        },
        {
            "attendance_id": 362,
            "employee_id": 2,
            "attendance_date": "2024-05-06T18:30:00.000Z",
            "status": "Present"
        },
        {
            "attendance_id": 363,
            "employee_id": 3,
            "attendance_date": "2024-05-06T18:30:00.000Z",
            "status": "Absent"
        },
        {
            "attendance_id": 364,
            "employee_id": 4,
            "attendance_date": "2024-05-06T18:30:00.000Z",
            "status": "Present"
        },
        {
            "attendance_id": 365,
            "employee_id": 5,
            "attendance_date": "2024-05-06T18:30:00.000Z",
            "status": "Present"
        },
        {
            "attendance_id": 366,
            "employee_id": 6,
            "attendance_date": "2024-05-06T18:30:00.000Z",
            "status": "Absent"
        },
        {
            "attendance_id": 367,
            "employee_id": 7,
            "attendance_date": "2024-05-06T18:30:00.000Z",
            "status": "Present"
        },
        {
            "attendance_id": 368,
            "employee_id": 8,
            "attendance_date": "2024-05-06T18:30:00.000Z",
            "status": "Present"
        },
        {
            "attendance_id": 369,
            "employee_id": 9,
            "attendance_date": "2024-05-06T18:30:00.000Z",
            "status": "Absent"
        },
        {
            "attendance_id": 370,
            "employee_id": 10,
            "attendance_date": "2024-05-06T18:30:00.000Z",
            "status": "Present"
        },
        {
            "attendance_id": 371,
            "employee_id": 1,
            "attendance_date": "2024-05-07T18:30:00.000Z",
            "status": "Present"
        },
        {
            "attendance_id": 372,
            "employee_id": 2,
            "attendance_date": "2024-05-07T18:30:00.000Z",
            "status": "Absent"
        },
        {
            "attendance_id": 373,
            "employee_id": 3,
            "attendance_date": "2024-05-07T18:30:00.000Z",
            "status": "Present"
        },
        {
            "attendance_id": 374,
            "employee_id": 4,
            "attendance_date": "2024-05-07T18:30:00.000Z",
            "status": "Present"
        },
        {
            "attendance_id": 375,
            "employee_id": 5,
            "attendance_date": "2024-05-07T18:30:00.000Z",
            "status": "Present"
        },
        {
            "attendance_id": 376,
            "employee_id": 6,
            "attendance_date": "2024-05-07T18:30:00.000Z",
            "status": "Absent"
        },
        {
            "attendance_id": 377,
            "employee_id": 7,
            "attendance_date": "2024-05-07T18:30:00.000Z",
            "status": "Present"
        },
        {
            "attendance_id": 378,
            "employee_id": 8,
            "attendance_date": "2024-05-07T18:30:00.000Z",
            "status": "Absent"
        },
        {
            "attendance_id": 379,
            "employee_id": 9,
            "attendance_date": "2024-05-07T18:30:00.000Z",
            "status": "Present"
        },
        {
            "attendance_id": 380,
            "employee_id": 10,
            "attendance_date": "2024-05-07T18:30:00.000Z",
            "status": "Present"
        },
        {
            "attendance_id": 381,
            "employee_id": 1,
            "attendance_date": "2024-05-08T18:30:00.000Z",
            "status": "Absent"
        },
        {
            "attendance_id": 382,
            "employee_id": 2,
            "attendance_date": "2024-05-08T18:30:00.000Z",
            "status": "Present"
        },
        {
            "attendance_id": 383,
            "employee_id": 3,
            "attendance_date": "2024-05-08T18:30:00.000Z",
            "status": "Present"
        },
        {
            "attendance_id": 384,
            "employee_id": 4,
            "attendance_date": "2024-05-08T18:30:00.000Z",
            "status": "Present"
        },
        {
            "attendance_id": 385,
            "employee_id": 5,
            "attendance_date": "2024-05-08T18:30:00.000Z",
            "status": "Present"
        },
        {
            "attendance_id": 386,
            "employee_id": 6,
            "attendance_date": "2024-05-08T18:30:00.000Z",
            "status": "Absent"
        },
        {
            "attendance_id": 387,
            "employee_id": 7,
            "attendance_date": "2024-05-08T18:30:00.000Z",
            "status": "Present"
        },
        {
            "attendance_id": 388,
            "employee_id": 8,
            "attendance_date": "2024-05-08T18:30:00.000Z",
            "status": "Present"
        },
        {
            "attendance_id": 389,
            "employee_id": 9,
            "attendance_date": "2024-05-08T18:30:00.000Z",
            "status": "Absent"
        },
        {
            "attendance_id": 390,
            "employee_id": 10,
            "attendance_date": "2024-05-08T18:30:00.000Z",
            "status": "Present"
        },
        {
            "attendance_id": 391,
            "employee_id": 1,
            "attendance_date": "2024-05-09T18:30:00.000Z",
            "status": "Present"
        },
        {
            "attendance_id": 392,
            "employee_id": 2,
            "attendance_date": "2024-05-09T18:30:00.000Z",
            "status": "Present"
        },
        {
            "attendance_id": 393,
            "employee_id": 3,
            "attendance_date": "2024-05-09T18:30:00.000Z",
            "status": "Absent"
        },
        {
            "attendance_id": 394,
            "employee_id": 4,
            "attendance_date": "2024-05-09T18:30:00.000Z",
            "status": "Present"
        },
        {
            "attendance_id": 395,
            "employee_id": 5,
            "attendance_date": "2024-05-09T18:30:00.000Z",
            "status": "Present"
        },
        {
            "attendance_id": 396,
            "employee_id": 6,
            "attendance_date": "2024-05-09T18:30:00.000Z",
            "status": "Absent"
        },
        {
            "attendance_id": 397,
            "employee_id": 7,
            "attendance_date": "2024-05-09T18:30:00.000Z",
            "status": "Present"
        },
        {
            "attendance_id": 398,
            "employee_id": 8,
            "attendance_date": "2024-05-09T18:30:00.000Z",
            "status": "Present"
        },
        {
            "attendance_id": 399,
            "employee_id": 9,
            "attendance_date": "2024-05-09T18:30:00.000Z",
            "status": "Absent"
        },
        {
            "attendance_id": 400,
            "employee_id": 10,
            "attendance_date": "2024-05-09T18:30:00.000Z",
            "status": "Present"
        }
    ]
}